athena_client/__init__.py
athena_client/async_client.py
athena_client/auth.py
athena_client/cli.py
athena_client/cli.py.fixed
athena_client/client.py
athena_client/concept_explorer.py
athena_client/concept_set.py
athena_client/exceptions.py
athena_client/http.py
athena_client/query.py
athena_client/search_result.py
athena_client/settings.py
athena_client/db/__init__.py
athena_client/db/base.py
athena_client/db/sqlalchemy_connector.py
athena_client/models/__init__.py
athena_client/utils/__init__.py
athena_client/utils/optional_deps.py
athena_client/utils/progress.py
athena_client/utils/user_agents.py
athena_client/py.typed
athena_client-1.0.32.dist-info/METADATA
athena_client-1.0.32.dist-info/WHEEL
athena_client-1.0.32.dist-info/entry_points.txt
athena_client-1.0.32.dist-info/licenses/LICENSE
athena_client-1.0.32.dist-info/RECORD
