Metadata-Version: 2.4
Name: athena-client
Version: 1.0.32
Summary: An unofficial Python SDK for interacting with the OHDSI Athena Concepts API.
Project-URL: Homepage, https://github.com/aandresalvarez/athena_client
Project-URL: Documentation, https://github.com/aandresalvarez/athena_client#readme
Project-URL: Issues, https://github.com/aandresalvarez/athena_client/issues
Project-URL: Repository, https://github.com/aandresalvarez/athena_client
Author: Alvaro A. Alvarez P. 
License: MIT
License-File: LICENSE
Requires-Python: >=3.9
Requires-Dist: backoff>=2.0.0
Requires-Dist: click>=8.0.0
Requires-Dist: httpx>=0.18.0
Requires-Dist: orjson>=3.9.0
Requires-Dist: pydantic-settings
Requires-Dist: pydantic>=2.0.0
Requires-Dist: requests>=2.0.0
Requires-Dist: rich>=10.0.0
Provides-Extra: all
Requires-Dist: backoff>=2.0.0; extra == 'all'
Requires-Dist: click>=8.0.0; extra == 'all'
Requires-Dist: cryptography>=36.0.0; extra == 'all'
Requires-Dist: httpx>=0.18.0; extra == 'all'
Requires-Dist: pandas<3.0.0,>=1.3.0; extra == 'all'
Requires-Dist: psycopg2-binary>=2.9.0; extra == 'all'
Requires-Dist: pyyaml>=6.0; extra == 'all'
Requires-Dist: rich>=10.0.0; extra == 'all'
Requires-Dist: sqlalchemy-bigquery; extra == 'all'
Requires-Dist: sqlalchemy>=1.4.0; extra == 'all'
Provides-Extra: async
Requires-Dist: backoff>=2.0.0; extra == 'async'
Requires-Dist: httpx>=0.18.0; extra == 'async'
Provides-Extra: bigquery
Requires-Dist: sqlalchemy-bigquery; extra == 'bigquery'
Requires-Dist: sqlalchemy>=1.4.0; extra == 'bigquery'
Provides-Extra: cli
Requires-Dist: click>=8.0.0; extra == 'cli'
Requires-Dist: rich>=10.0.0; extra == 'cli'
Provides-Extra: core
Requires-Dist: backoff>=2.0.0; extra == 'core'
Requires-Dist: httpx>=0.18.0; extra == 'core'
Requires-Dist: orjson>=3.9.0; extra == 'core'
Requires-Dist: pydantic-settings; extra == 'core'
Requires-Dist: pydantic>=2.0.0; extra == 'core'
Provides-Extra: crypto
Requires-Dist: cryptography>=36.0.0; extra == 'crypto'
Provides-Extra: db
Requires-Dist: psycopg2-binary>=2.9.0; extra == 'db'
Requires-Dist: sqlalchemy-bigquery; extra == 'db'
Requires-Dist: sqlalchemy>=1.4.0; extra == 'db'
Provides-Extra: dev
Requires-Dist: bandit>=1.7.5; extra == 'dev'
Requires-Dist: build>=1.2; extra == 'dev'
Requires-Dist: cyclonedx-bom>=3.15.0; extra == 'dev'
Requires-Dist: cyclonedx-python-lib>=5.2.0; extra == 'dev'
Requires-Dist: hatch; extra == 'dev'
Requires-Dist: hatchling; extra == 'dev'
Requires-Dist: hypothesis>=6.103; extra == 'dev'
Requires-Dist: mypy>=1.10; extra == 'dev'
Requires-Dist: packaging>=21.0; extra == 'dev'
Requires-Dist: pandas-stubs; extra == 'dev'
Requires-Dist: pip-audit>=2.6; extra == 'dev'
Requires-Dist: pytest-asyncio[mode-auto]>=0.23; extra == 'dev'
Requires-Dist: pytest-benchmark>=4.0; extra == 'dev'
Requires-Dist: pytest-cov>=5.0; extra == 'dev'
Requires-Dist: pytest>=8.2; extra == 'dev'
Requires-Dist: rich>=13.7; extra == 'dev'
Requires-Dist: ruff>=0.4.0; extra == 'dev'
Requires-Dist: sqlalchemy-stubs; extra == 'dev'
Requires-Dist: tomli>=2.0.0; (python_version < '3.11') and extra == 'dev'
Requires-Dist: twine>=5.1; extra == 'dev'
Requires-Dist: types-pyyaml; extra == 'dev'
Requires-Dist: types-requests; extra == 'dev'
Requires-Dist: vcrpy>=6.0; extra == 'dev'
Provides-Extra: full
Requires-Dist: click>=8.0.0; extra == 'full'
Requires-Dist: cryptography>=36.0.0; extra == 'full'
Requires-Dist: pandas<3.0.0,>=1.3.0; extra == 'full'
Requires-Dist: psycopg2-binary>=2.9.0; extra == 'full'
Requires-Dist: pyyaml>=6.0; extra == 'full'
Requires-Dist: rich>=10.0.0; extra == 'full'
Requires-Dist: sqlalchemy-bigquery; extra == 'full'
Requires-Dist: sqlalchemy>=1.4.0; extra == 'full'
Provides-Extra: pandas
Requires-Dist: pandas<3.0.0,>=1.3.0; extra == 'pandas'
Provides-Extra: postgres
Requires-Dist: psycopg2-binary>=2.9.0; extra == 'postgres'
Requires-Dist: sqlalchemy>=1.4.0; extra == 'postgres'
Provides-Extra: yaml
Requires-Dist: pyyaml>=6.0; extra == 'yaml'
